dabcli/__init__.py
dabcli/album.py
dabcli/api.py
dabcli/artist.py
dabcli/cli.py
dabcli/config.py
dabcli/cover.py
dabcli/downloader.py
dabcli/library.py
dabcli/search.py
dabcli/streamer.py
dabcli/tagger.py
dabcli/utils.py
dabcli/version.py
dabcli/assets/silence.flac
dabcli-2.1.7.dist-info/licenses/LICENSE
dabcli-2.1.7.dist-info/METADATA
dabcli-2.1.7.dist-info/WHEEL
dabcli-2.1.7.dist-info/entry_points.txt
dabcli-2.1.7.dist-info/top_level.txt
dabcli-2.1.7.dist-info/RECORD
