Metadata-Version: 2.4
Name: dabcli
Version: 2.1.7
Summary: DAB CLI — A command-line interface for browsing and downloading music from DAB Music Player.
Author-email: sherlockholmesat221b <sherlockholmesat221b@proton.me>
License-Expression: MIT
Project-URL: Homepage, https://github.com/sherlockholmesat221b/dabcli
Project-URL: Issues, https://github.com/sherlockholmesat221b/dabcli/issues
Keywords: music,DAB,CLI,downloader
Classifier: Development Status :: 4 - Beta
Classifier: Intended Audience :: End Users/Desktop
Classifier: Programming Language :: Python :: 3
Classifier: Programming Language :: Python :: 3.9
Classifier: Programming Language :: Python :: 3.10
Classifier: Programming Language :: Python :: 3.11
Classifier: Operating System :: OS Independent
Classifier: Topic :: Multimedia :: Sound/Audio
Requires-Python: >=3.9
License-File: LICENSE
Requires-Dist: requests>=2.31
Requires-Dist: tqdm>=4.66
Requires-Dist: mutagen>=1.47
Requires-Dist: tabulate>=0.9
Requires-Dist: platformdirs>=4.0
Dynamic: license-file
